armanfirstpackage/__init__.py
armanfirstpackage/a.py
armanfirstpackage/b.py
armanfirstpackage-0.0.3.dist-info/METADATA
armanfirstpackage-0.0.3.dist-info/WHEEL
armanfirstpackage-0.0.3.dist-info/top_level.txt
armanfirstpackage-0.0.3.dist-info/RECORD
