Metadata-Version: 2.1
Name: armanfirstpackage
Version: 0.0.3
Summary: My first Python package
Home-page: UNKNOWN
Author: Md. Arman Hossain
Author-email: shanto377@gmail.com
License: UNKNOWN
Keywords: python,first package
Platform: UNKNOWN
Classifier: Development Status :: 3 - Alpha
Classifier: Intended Audience :: Education
Classifier: Programming Language :: Python :: 3
Classifier: Operating System :: OS Independent
